pagebotosx/__init__.py
pagebotosx/errors.py
pagebotosx/osxcolor.py
pagebotosx/contexts/__init__.py
pagebotosx/contexts/drawbotcontext/__init__.py
pagebotosx/contexts/drawbotcontext/drawbotcontext.py
pagebotosx/contexts/sketchcontext/__init__.py
pagebotosx/contexts/sketchcontext/sketchbuilder.py
pagebotosx/contexts/sketchcontext/sketchcontext.py
pagebotosx/graphics/__init__.py
pagebotosx/graphics/graphic.py
pagebotosx/mathematics/__init__.py
pagebotosx/mathematics/transform.py
pagebotosx/strings/__init__.py
pagebotosx/strings/pattern.py
pagebotosx/strings/tmp.py
pagebotosx/strings/tryinstallfont.py
pagebotosx-1.0.3.dist-info/LICENSE.md
pagebotosx-1.0.3.dist-info/METADATA
pagebotosx-1.0.3.dist-info/WHEEL
pagebotosx-1.0.3.dist-info/dependency_links.txt
pagebotosx-1.0.3.dist-info/top_level.txt
pagebotosx-1.0.3.dist-info/RECORD
