Metadata-Version: 2.1
Name: pagebotosx
Version: 1.0.3
Summary: OS X only contexts for PageBot.
Home-page: https://github.com/PageBot/PageBotOSX
Author: Petr van Blokland, Michiel Kauw-A-Tjoe
Author-email: r@petr.com
License: MIT
Platform: UNKNOWN
Classifier: Development Status :: 3 - Alpha
Classifier: Intended Audience :: Developers
Classifier: Intended Audience :: Other Audience
Classifier: License :: OSI Approved :: MIT License
Classifier: Operating System :: MacOS
Classifier: Programming Language :: Python :: 3.6
Classifier: Topic :: Artistic Software
Classifier: Topic :: Multimedia :: Graphics
Classifier: Topic :: Multimedia :: Graphics :: Editors
Classifier: Topic :: Multimedia :: Graphics :: Editors :: Raster-Based
Classifier: Topic :: Multimedia :: Graphics :: Editors :: Vector-Based
Classifier: Topic :: Multimedia :: Graphics :: Graphics Conversion
Classifier: Topic :: Multimedia :: Graphics :: Viewers
Classifier: Topic :: Scientific/Engineering :: Visualization
Classifier: Topic :: Software Development :: Libraries
Classifier: Topic :: Software Development :: Libraries :: Python Modules
Classifier: Topic :: Text Processing
Classifier: Topic :: Text Processing :: Fonts
Requires-Dist: pyobjc
Requires-Dist: pagebot
Requires-Dist: drawbot
Requires-Dist: pysketch
